[{"link":{"from":{"isCustom":true,"id":47546,"label":"PROG ZRESOURCE","title":"Capacity Evaluation Report - By Work Center","technicalName":"ZRESOURCE","group":"PROG"},"edge":{"from":47546,"id":"47546-33028","to":33028,"label":null},"to":{"isCustom":true,"id":33028,"label":"INCL ZCL_PS_UTIL===================CU","title":null,"technicalName":"ZCL_PS_UTIL===================CU","group":"PROG"}}},{"link":{"from":{"isCustom":true,"id":47546,"label":"PROG ZRESOURCE","title":"Capacity Evaluation Report - By Work Center","technicalName":"ZRESOURCE","group":"PROG"},"edge":{"from":47546,"id":"47546-1084077","to":1084077,"label":null},"to":{"isCustom":true,"id":1084077,"label":"TTYP ZP_STATUS_OUT","title":null,"technicalName":"ZP_STATUS_OUT","group":"TTYP"}}},{"link":{"from":{"isCustom":true,"id":1084077,"label":"TTYP ZP_STATUS_OUT","title":null,"technicalName":"ZP_STATUS_OUT","group":"TTYP"},"edge":{"from":1084077,"id":"1084077-59539","to":59539,"label":null},"to":{"isCustom":true,"id":59539,"label":"STRU ZZOBJ_STAT","title":"Object number and status","technicalName":"ZZOBJ_STAT","group":"STRU"}}},{"link":{"from":{"isCustom":true,"id":47546,"label":"PROG ZRESOURCE","title":"Capacity Evaluation Report - By Work Center","technicalName":"ZRESOURCE","group":"PROG"},"edge":{"from":47546,"id":"47546-1083897","to":1083897,"label":null},"to":{"isCustom":false,"id":1083897,"label":"TRAN CM01","title":null,"technicalName":"CM01","group":"TRAN"}}},{"link":{"from":{"isCustom":true,"id":47546,"label":"PROG ZRESOURCE","title":"Capacity Evaluation Report - By Work Center","technicalName":"ZRESOURCE","group":"PROG"},"edge":{"from":47546,"id":"47546-1083643","to":1083643,"label":null},"to":{"isCustom":false,"id":1083643,"label":"TRAN CN22","title":null,"technicalName":"CN22","group":"TRAN"}}},{"link":{"from":{"isCustom":false,"id":1083643,"label":"TRAN CN22","title":null,"technicalName":"CN22","group":"TRAN"},"edge":{"from":1083643,"id":"1083643-48931","to":48931,"label":null},"to":{"isCustom":false,"id":48931,"label":"FUGR COKO","title":null,"technicalName":"SAPLCOKO","group":"PROG"}}},{"link":{"from":{"isCustom":false,"id":48931,"label":"FUGR COKO","title":null,"technicalName":"SAPLCOKO","group":"PROG"},"edge":{"from":48931,"id":"48931-33005","to":33005,"label":null},"to":{"isCustom":true,"id":33005,"label":"INCL ZCL_PS_CHK_EMPLOYEE===========CU","title":null,"technicalName":"ZCL_PS_CHK_EMPLOYEE===========CU","group":"PROG"}}},{"link":{"from":{"isCustom":true,"id":47546,"label":"PROG ZRESOURCE","title":"Capacity Evaluation Report - By Work Center","technicalName":"ZRESOURCE","group":"PROG"},"edge":{"from":47546,"id":"47546-1083705","to":1083705,"label":null},"to":{"isCustom":false,"id":1083705,"label":"TRAN CN23","title":null,"technicalName":"CN23","group":"TRAN"}}},{"link":{"from":{"isCustom":false,"id":1083705,"label":"TRAN CN23","title":null,"technicalName":"CN23","group":"TRAN"},"edge":{"from":1083705,"id":"1083705-48931","to":48931,"label":null},"to":{"isCustom":false,"id":48931,"label":"FUGR COKO","title":null,"technicalName":"SAPLCOKO","group":"PROG"}}},{"link":{"from":{"isCustom":true,"id":47546,"label":"PROG ZRESOURCE","title":"Capacity Evaluation Report - By Work Center","technicalName":"ZRESOURCE","group":"PROG"},"edge":{"from":47546,"id":"47546-1083898","to":1083898,"label":null},"to":{"isCustom":false,"id":1083898,"label":"TRAN CNR3","title":null,"technicalName":"CNR3","group":"TRAN"}}},{"link":{"from":{"isCustom":true,"id":47546,"label":"PROG ZRESOURCE","title":"Capacity Evaluation Report - By Work Center","technicalName":"ZRESOURCE","group":"PROG"},"edge":{"from":47546,"id":"47546-104849","to":104849,"label":null},"to":{"isCustom":false,"id":104849,"label":"TABL KAZY","title":"Interval of Available Capacity","technicalName":"KAZY","group":"TABL"}}},{"link":{"from":{"isCustom":true,"id":47546,"label":"PROG ZRESOURCE","title":"Capacity Evaluation Report - By Work Center","technicalName":"ZRESOURCE","group":"PROG"},"edge":{"from":47546,"id":"47546-104854","to":104854,"label":null},"to":{"isCustom":false,"id":104854,"label":"TABL KBEZ","title":"Add. data for table KBED (for indiv. capacities/splits)","technicalName":"KBEZ","group":"TABL"}}},{"link":{"from":{"isCustom":true,"id":47546,"label":"PROG ZRESOURCE","title":"Capacity Evaluation Report - By Work Center","technicalName":"ZRESOURCE","group":"PROG"},"edge":{"from":47546,"id":"47546-103916","to":103916,"label":null},"to":{"isCustom":false,"id":103916,"label":"TABL JEST","title":"Individual Object Status","technicalName":"JEST","group":"TABL"}}},{"link":{"from":{"isCustom":true,"id":47546,"label":"PROG ZRESOURCE","title":"Capacity Evaluation Report - By Work Center","technicalName":"ZRESOURCE","group":"PROG"},"edge":{"from":47546,"id":"47546-79265","to":79265,"label":null},"to":{"isCustom":false,"id":79265,"label":"TABL AFVV","title":"DB structure of the quantities/dates/values in the operation","technicalName":"AFVV","group":"TABL"}}},{"link":{"from":{"isCustom":true,"id":47546,"label":"PROG ZRESOURCE","title":"Capacity Evaluation Report - By Work Center","technicalName":"ZRESOURCE","group":"PROG"},"edge":{"from":47546,"id":"47546-86454","to":86454,"label":null},"to":{"isCustom":false,"id":86454,"label":"TABL CRHS","title":"Hierarchy Structure","technicalName":"CRHS","group":"TABL"}}},{"link":{"from":{"isCustom":true,"id":47546,"label":"PROG ZRESOURCE","title":"Capacity Evaluation Report - By Work Center","technicalName":"ZRESOURCE","group":"PROG"},"edge":{"from":47546,"id":"47546-86083","to":86083,"label":null},"to":{"isCustom":false,"id":86083,"label":"TABL COSS","title":"CO Object: Cost Totals for Internal Postings","technicalName":"COSS","group":"TABL"}}},{"link":{"from":{"isCustom":true,"id":47546,"label":"PROG ZRESOURCE","title":"Capacity Evaluation Report - By Work Center","technicalName":"ZRESOURCE","group":"PROG"},"edge":{"from":47546,"id":"47546-116703","to":116703,"label":null},"to":{"isCustom":false,"id":116703,"label":"TABL PRPS","title":"WBS (Work Breakdown Structure) Element Master Data","technicalName":"PRPS","group":"TABL"}}},{"link":{"from":{"isCustom":true,"id":47546,"label":"PROG ZRESOURCE","title":"Capacity Evaluation Report - By Work Center","technicalName":"ZRESOURCE","group":"PROG"},"edge":{"from":47546,"id":"47546-79259","to":79259,"label":null},"to":{"isCustom":false,"id":79259,"label":"TABL AFVC","title":"Operation within an order","technicalName":"AFVC","group":"TABL"}}},{"link":{"from":{"isCustom":true,"id":47546,"label":"PROG ZRESOURCE","title":"Capacity Evaluation Report - By Work Center","technicalName":"ZRESOURCE","group":"PROG"},"edge":{"from":47546,"id":"47546-79253","to":79253,"label":null},"to":{"isCustom":false,"id":79253,"label":"TABL AFRU","title":"Order Confirmations","technicalName":"AFRU","group":"TABL"}}},{"link":{"from":{"isCustom":true,"id":47546,"label":"PROG ZRESOURCE","title":"Capacity Evaluation Report - By Work Center","technicalName":"ZRESOURCE","group":"PROG"},"edge":{"from":47546,"id":"47546-104850","to":104850,"label":null},"to":{"isCustom":false,"id":104850,"label":"TABL KBED","title":"Capacity Requirements Records","technicalName":"KBED","group":"TABL"}}},{"link":{"from":{"isCustom":true,"id":47546,"label":"PROG ZRESOURCE","title":"Capacity Evaluation Report - By Work Center","technicalName":"ZRESOURCE","group":"PROG"},"edge":{"from":47546,"id":"47546-104846","to":104846,"label":null},"to":{"isCustom":false,"id":104846,"label":"TABL KAPA","title":"Shift Parameters for Available Capacity","technicalName":"KAPA","group":"TABL"}}},{"link":{"from":{"isCustom":true,"id":47546,"label":"PROG ZRESOURCE","title":"Capacity Evaluation Report - By Work Center","technicalName":"ZRESOURCE","group":"PROG"},"edge":{"from":47546,"id":"47546-86453","to":86453,"label":null},"to":{"isCustom":false,"id":86453,"label":"TABL CRHH","title":"Hierarchy Header Data","technicalName":"CRHH","group":"TABL"}}},{"link":{"from":{"isCustom":true,"id":47546,"label":"PROG ZRESOURCE","title":"Capacity Evaluation Report - By Work Center","technicalName":"ZRESOURCE","group":"PROG"},"edge":{"from":47546,"id":"47546-147044","to":147044,"label":null},"to":{"isCustom":false,"id":147044,"label":"TABL TCN7T","title":"Text table for priorities (TCN07)","technicalName":"TCN7T","group":"TABL"}}},{"link":{"from":{"isCustom":true,"id":47546,"label":"PROG ZRESOURCE","title":"Capacity Evaluation Report - By Work Center","technicalName":"ZRESOURCE","group":"PROG"},"edge":{"from":47546,"id":"47546-104819","to":104819,"label":null},"to":{"isCustom":false,"id":104819,"label":"TABL KAKO","title":"Capacity Header Segment","technicalName":"KAKO","group":"TABL"}}},{"link":{"from":{"isCustom":true,"id":47546,"label":"PROG ZRESOURCE","title":"Capacity Evaluation Report - By Work Center","technicalName":"ZRESOURCE","group":"PROG"},"edge":{"from":47546,"id":"47546-79180","to":79180,"label":null},"to":{"isCustom":false,"id":79180,"label":"TABL AFKO","title":"Order Header Data PP Orders","technicalName":"AFKO","group":"TABL"}}},{"link":{"from":{"isCustom":true,"id":47546,"label":"PROG ZRESOURCE","title":"Capacity Evaluation Report - By Work Center","technicalName":"ZRESOURCE","group":"PROG"},"edge":{"from":47546,"id":"47546-86452","to":86452,"label":null},"to":{"isCustom":false,"id":86452,"label":"TABL CRHD","title":"Work Center Header","technicalName":"CRHD","group":"TABL"}}},{"link":{"from":{"isCustom":true,"id":47546,"label":"PROG ZRESOURCE","title":"Capacity Evaluation Report - By Work Center","technicalName":"ZRESOURCE","group":"PROG"},"edge":{"from":47546,"id":"47546-128054","to":128054,"label":null},"to":{"isCustom":false,"id":128054,"label":"TABL T024A","title":"Planner group","technicalName":"T024A","group":"TABL"}}},{"link":{"from":{"isCustom":true,"id":47546,"label":"PROG ZRESOURCE","title":"Capacity Evaluation Report - By Work Center","technicalName":"ZRESOURCE","group":"PROG"},"edge":{"from":47546,"id":"47546-104545","to":104545,"label":null},"to":{"isCustom":false,"id":104545,"label":"TABL JSTO","title":"Status object information","technicalName":"JSTO","group":"TABL"}}},{"link":{"from":{"isCustom":true,"id":47546,"label":"PROG ZRESOURCE","title":"Capacity Evaluation Report - By Work Center","technicalName":"ZRESOURCE","group":"PROG"},"edge":{"from":47546,"id":"47546-124956","to":124956,"label":null},"to":{"isCustom":false,"id":124956,"label":"TABL SMLT","title":"Standard milestone description","technicalName":"SMLT","group":"TABL"}}},{"link":{"from":{"isCustom":true,"id":47546,"label":"PROG ZRESOURCE","title":"Capacity Evaluation Report - By Work Center","technicalName":"ZRESOURCE","group":"PROG"},"edge":{"from":47546,"id":"47546-67305","to":67305,"label":null},"to":{"isCustom":true,"id":67305,"label":"TABL ZJTRIGGER","title":"Network Job Trigger - ZJTRIGGER","technicalName":"ZJTRIGGER","group":"TABL"}}},{"link":{"from":{"isCustom":true,"id":47546,"label":"PROG ZRESOURCE","title":"Capacity Evaluation Report - By Work Center","technicalName":"ZRESOURCE","group":"PROG"},"edge":{"from":47546,"id":"47546-80432","to":80432,"label":null},"to":{"isCustom":false,"id":80432,"label":"TABL AUFK","title":"Order master data","technicalName":"AUFK","group":"TABL"}}},{"link":{"from":{"isCustom":true,"id":47546,"label":"PROG ZRESOURCE","title":"Capacity Evaluation Report - By Work Center","technicalName":"ZRESOURCE","group":"PROG"},"edge":{"from":47546,"id":"47546-79263","to":79263,"label":null},"to":{"isCustom":false,"id":79263,"label":"TABL AFVU","title":"DB structure of the user fields of the operation","technicalName":"AFVU","group":"TABL"}}},{"link":{"from":{"isCustom":true,"id":47546,"label":"PROG ZRESOURCE","title":"Capacity Evaluation Report - By Work Center","technicalName":"ZRESOURCE","group":"PROG"},"edge":{"from":47546,"id":"47546-103894","to":103894,"label":null},"to":{"isCustom":false,"id":103894,"label":"TABL JCDS","title":"Change Documents for System/User Statuses (Table JEST)","technicalName":"JCDS","group":"TABL"}}},{"link":{"from":{"isCustom":true,"id":47546,"label":"PROG ZRESOURCE","title":"Capacity Evaluation Report - By Work Center","technicalName":"ZRESOURCE","group":"PROG"},"edge":{"from":47546,"id":"47546-99022","to":99022,"label":null},"to":{"isCustom":false,"id":99022,"label":"TABL HRP1000","title":"Infotype 1000 DB Table","technicalName":"HRP1000","group":"TABL"}}},{"link":{"from":{"isCustom":true,"id":47546,"label":"PROG ZRESOURCE","title":"Capacity Evaluation Report - By Work Center","technicalName":"ZRESOURCE","group":"PROG"},"edge":{"from":47546,"id":"47546-154063","to":154063,"label":null},"to":{"isCustom":false,"id":154063,"label":"TABL TJ30T","title":"Texts for User Status","technicalName":"TJ30T","group":"TABL"}}},{"link":{"from":{"isCustom":true,"id":47546,"label":"PROG ZRESOURCE","title":"Capacity Evaluation Report - By Work Center","technicalName":"ZRESOURCE","group":"PROG"},"edge":{"from":47546,"id":"47546-65918","to":65918,"label":null},"to":{"isCustom":true,"id":65918,"label":"TABL ZCC_TR_ARIBA","title":"Cross Company Code Project to Internal Order # mapping","technicalName":"ZCC_TR_ARIBA","group":"TABL"}}},{"link":{"from":{"isCustom":true,"id":47546,"label":"PROG ZRESOURCE","title":"Capacity Evaluation Report - By Work Center","technicalName":"ZRESOURCE","group":"PROG"},"edge":{"from":47546,"id":"47546-114452","to":114452,"label":null},"to":{"isCustom":false,"id":114452,"label":"TABL PA0002","title":"HR Master Record: Infotype 0002 (Personal Data)","technicalName":"PA0002","group":"TABL"}}},{"link":{"from":{"isCustom":true,"id":47546,"label":"PROG ZRESOURCE","title":"Capacity Evaluation Report - By Work Center","technicalName":"ZRESOURCE","group":"PROG"},"edge":{"from":47546,"id":"47546-108041","to":108041,"label":null},"to":{"isCustom":false,"id":108041,"label":"TABL MLTX","title":"Milestone Description","technicalName":"MLTX","group":"TABL"}}},{"link":{"from":{"isCustom":true,"id":47546,"label":"PROG ZRESOURCE","title":"Capacity Evaluation Report - By Work Center","technicalName":"ZRESOURCE","group":"PROG"},"edge":{"from":47546,"id":"47546-154041","to":154041,"label":null},"to":{"isCustom":false,"id":154041,"label":"TABL TJ02T","title":"System status texts","technicalName":"TJ02T","group":"TABL"}}},{"link":{"from":{"isCustom":true,"id":47546,"label":"PROG ZRESOURCE","title":"Capacity Evaluation Report - By Work Center","technicalName":"ZRESOURCE","group":"PROG"},"edge":{"from":47546,"id":"47546-108033","to":108033,"label":null},"to":{"isCustom":false,"id":108033,"label":"TABL MLST","title":"Milestone","technicalName":"MLST","group":"TABL"}}},{"link":{"from":{"isCustom":true,"id":47546,"label":"PROG ZRESOURCE","title":"Capacity Evaluation Report - By Work Center","technicalName":"ZRESOURCE","group":"PROG"},"edge":{"from":47546,"id":"47546-128057","to":128057,"label":null},"to":{"isCustom":false,"id":128057,"label":"TABL T024D","title":"MRP controllers","technicalName":"T024D","group":"TABL"}}},{"link":{"from":{"isCustom":true,"id":47546,"label":"PROG ZRESOURCE","title":"Capacity Evaluation Report - By Work Center","technicalName":"ZRESOURCE","group":"PROG"},"edge":{"from":47546,"id":"47546-114451","to":114451,"label":null},"to":{"isCustom":false,"id":114451,"label":"TABL PA0001","title":"HR Master Record: Infotype 0001 (Org. Assignment)","technicalName":"PA0001","group":"TABL"}}},{"link":{"from":{"isCustom":true,"id":47546,"label":"PROG ZRESOURCE","title":"Capacity Evaluation Report - By Work Center","technicalName":"ZRESOURCE","group":"PROG"},"edge":{"from":47546,"id":"47546-334677","to":334677,"label":null},"to":{"isCustom":false,"id":334677,"label":"STRU HELP_VALUE","title":"Structure or Function Module HELP_VALUE_GET_FOR_TABLE","technicalName":"HELP_VALUE","group":"STRU"}}},{"link":{"from":{"isCustom":true,"id":47546,"label":"PROG ZRESOURCE","title":"Capacity Evaluation Report - By Work Center","technicalName":"ZRESOURCE","group":"PROG"},"edge":{"from":47546,"id":"47546-1082912","to":1082912,"label":null},"to":{"isCustom":false,"id":1082912,"label":"METH ##W_OREF_MNT->/MRSS/IF_SGE_MNT_RESOURCES~ASSIGNMENTS_SELECT_EXT","title":null,"technicalName":"##W_OREF_MNT->/MRSS/IF_SGE_MNT_RESOURCES~ASSIGNMENTS_SELECT_EXT","group":"PROG"}}},{"link":{"from":{"isCustom":true,"id":47546,"label":"PROG ZRESOURCE","title":"Capacity Evaluation Report - By Work Center","technicalName":"ZRESOURCE","group":"PROG"},"edge":{"from":47546,"id":"47546-1081472","to":1081472,"label":null},"to":{"isCustom":false,"id":1081472,"label":"METH ##/MRSS/CL_SGE_APPLICATION_MNT=>GET_INSTANCE_OF","title":null,"technicalName":"##/MRSS/CL_SGE_APPLICATION_MNT=>GET_INSTANCE_OF","group":"PROG"}}},{"link":{"from":{"isCustom":true,"id":47546,"label":"PROG ZRESOURCE","title":"Capacity Evaluation Report - By Work Center","technicalName":"ZRESOURCE","group":"PROG"},"edge":{"from":47546,"id":"47546-33025","to":33025,"label":null},"to":{"isCustom":true,"id":33025,"label":"METH ZCL_PS_UTIL===================CM001","title":null,"technicalName":"ZCL_PS_UTIL===================CM001","group":"PROG"}}},{"link":{"from":{"isCustom":true,"id":33025,"label":"METH ZCL_PS_UTIL===================CM001","title":null,"technicalName":"ZCL_PS_UTIL===================CM001","group":"PROG"},"edge":{"from":33025,"id":"33025-103916","to":103916,"label":null},"to":{"isCustom":false,"id":103916,"label":"TABL JEST","title":"Individual Object Status","technicalName":"JEST","group":"TABL"}}},{"link":{"from":{"isCustom":true,"id":47546,"label":"PROG ZRESOURCE","title":"Capacity Evaluation Report - By Work Center","technicalName":"ZRESOURCE","group":"PROG"},"edge":{"from":47546,"id":"47546-1077958","to":1077958,"label":null},"to":{"isCustom":false,"id":1077958,"label":"INCL <ICON>","title":null,"technicalName":"<ICON>","group":"PROG"}}},{"link":{"from":{"isCustom":true,"id":47546,"label":"PROG ZRESOURCE","title":"Capacity Evaluation Report - By Work Center","technicalName":"ZRESOURCE","group":"PROG"},"edge":{"from":47546,"id":"47546-36282","to":36282,"label":null},"to":{"isCustom":true,"id":36282,"label":"INCL ZRESOURCE_TOP","title":"Include ZRESOURCE_TOP","technicalName":"ZRESOURCE_TOP","group":"PROG"}}},{"link":{"from":{"isCustom":true,"id":36282,"label":"INCL ZRESOURCE_TOP","title":"Include ZRESOURCE_TOP","technicalName":"ZRESOURCE_TOP","group":"PROG"},"edge":{"from":36282,"id":"36282-1084500","to":1084500,"label":null},"to":{"isCustom":false,"id":1084500,"label":"TYPE ICON","title":null,"technicalName":"ICON","group":"TYPE"}}},{"link":{"from":{"isCustom":true,"id":36282,"label":"INCL ZRESOURCE_TOP","title":"Include ZRESOURCE_TOP","technicalName":"ZRESOURCE_TOP","group":"PROG"},"edge":{"from":36282,"id":"36282-1084494","to":1084494,"label":null},"to":{"isCustom":false,"id":1084494,"label":"TYPE SLIS","title":null,"technicalName":"SLIS","group":"TYPE"}}},{"link":{"from":{"isCustom":true,"id":36282,"label":"INCL ZRESOURCE_TOP","title":"Include ZRESOURCE_TOP","technicalName":"ZRESOURCE_TOP","group":"PROG"},"edge":{"from":36282,"id":"36282-1084077","to":1084077,"label":null},"to":{"isCustom":true,"id":1084077,"label":"TTYP ZP_STATUS_OUT","title":null,"technicalName":"ZP_STATUS_OUT","group":"TTYP"}}},{"link":{"from":{"isCustom":true,"id":36282,"label":"INCL ZRESOURCE_TOP","title":"Include ZRESOURCE_TOP","technicalName":"ZRESOURCE_TOP","group":"PROG"},"edge":{"from":36282,"id":"36282-1084076","to":1084076,"label":null},"to":{"isCustom":true,"id":1084076,"label":"TTYP ZP_STATUS_IN","title":null,"technicalName":"ZP_STATUS_IN","group":"TTYP"}}},{"link":{"from":{"isCustom":true,"id":36282,"label":"INCL ZRESOURCE_TOP","title":"Include ZRESOURCE_TOP","technicalName":"ZRESOURCE_TOP","group":"PROG"},"edge":{"from":36282,"id":"36282-104819","to":104819,"label":null},"to":{"isCustom":false,"id":104819,"label":"TABL KAKO","title":"Capacity Header Segment","technicalName":"KAKO","group":"TABL"}}},{"link":{"from":{"isCustom":true,"id":36282,"label":"INCL ZRESOURCE_TOP","title":"Include ZRESOURCE_TOP","technicalName":"ZRESOURCE_TOP","group":"PROG"},"edge":{"from":36282,"id":"36282-104846","to":104846,"label":null},"to":{"isCustom":false,"id":104846,"label":"TABL KAPA","title":"Shift Parameters for Available Capacity","technicalName":"KAPA","group":"TABL"}}},{"link":{"from":{"isCustom":true,"id":36282,"label":"INCL ZRESOURCE_TOP","title":"Include ZRESOURCE_TOP","technicalName":"ZRESOURCE_TOP","group":"PROG"},"edge":{"from":36282,"id":"36282-86453","to":86453,"label":null},"to":{"isCustom":false,"id":86453,"label":"TABL CRHH","title":"Hierarchy Header Data","technicalName":"CRHH","group":"TABL"}}},{"link":{"from":{"isCustom":true,"id":36282,"label":"INCL ZRESOURCE_TOP","title":"Include ZRESOURCE_TOP","technicalName":"ZRESOURCE_TOP","group":"PROG"},"edge":{"from":36282,"id":"36282-114451","to":114451,"label":null},"to":{"isCustom":false,"id":114451,"label":"TABL PA0001","title":"HR Master Record: Infotype 0001 (Org. Assignment)","technicalName":"PA0001","group":"TABL"}}},{"link":{"from":{"isCustom":true,"id":36282,"label":"INCL ZRESOURCE_TOP","title":"Include ZRESOURCE_TOP","technicalName":"ZRESOURCE_TOP","group":"PROG"},"edge":{"from":36282,"id":"36282-79180","to":79180,"label":null},"to":{"isCustom":false,"id":79180,"label":"TABL AFKO","title":"Order Header Data PP Orders","technicalName":"AFKO","group":"TABL"}}},{"link":{"from":{"isCustom":true,"id":36282,"label":"INCL ZRESOURCE_TOP","title":"Include ZRESOURCE_TOP","technicalName":"ZRESOURCE_TOP","group":"PROG"},"edge":{"from":36282,"id":"36282-124956","to":124956,"label":null},"to":{"isCustom":false,"id":124956,"label":"TABL SMLT","title":"Standard milestone description","technicalName":"SMLT","group":"TABL"}}},{"link":{"from":{"isCustom":true,"id":36282,"label":"INCL ZRESOURCE_TOP","title":"Include ZRESOURCE_TOP","technicalName":"ZRESOURCE_TOP","group":"PROG"},"edge":{"from":36282,"id":"36282-79265","to":79265,"label":null},"to":{"isCustom":false,"id":79265,"label":"TABL AFVV","title":"DB structure of the quantities/dates/values in the operation","technicalName":"AFVV","group":"TABL"}}},{"link":{"from":{"isCustom":true,"id":36282,"label":"INCL ZRESOURCE_TOP","title":"Include ZRESOURCE_TOP","technicalName":"ZRESOURCE_TOP","group":"PROG"},"edge":{"from":36282,"id":"36282-103894","to":103894,"label":null},"to":{"isCustom":false,"id":103894,"label":"TABL JCDS","title":"Change Documents for System/User Statuses (Table JEST)","technicalName":"JCDS","group":"TABL"}}},{"link":{"from":{"isCustom":true,"id":36282,"label":"INCL ZRESOURCE_TOP","title":"Include ZRESOURCE_TOP","technicalName":"ZRESOURCE_TOP","group":"PROG"},"edge":{"from":36282,"id":"36282-154063","to":154063,"label":null},"to":{"isCustom":false,"id":154063,"label":"TABL TJ30T","title":"Texts for User Status","technicalName":"TJ30T","group":"TABL"}}},{"link":{"from":{"isCustom":true,"id":36282,"label":"INCL ZRESOURCE_TOP","title":"Include ZRESOURCE_TOP","technicalName":"ZRESOURCE_TOP","group":"PROG"},"edge":{"from":36282,"id":"36282-79253","to":79253,"label":null},"to":{"isCustom":false,"id":79253,"label":"TABL AFRU","title":"Order Confirmations","technicalName":"AFRU","group":"TABL"}}},{"link":{"from":{"isCustom":true,"id":36282,"label":"INCL ZRESOURCE_TOP","title":"Include ZRESOURCE_TOP","technicalName":"ZRESOURCE_TOP","group":"PROG"},"edge":{"from":36282,"id":"36282-104850","to":104850,"label":null},"to":{"isCustom":false,"id":104850,"label":"TABL KBED","title":"Capacity Requirements Records","technicalName":"KBED","group":"TABL"}}},{"link":{"from":{"isCustom":true,"id":36282,"label":"INCL ZRESOURCE_TOP","title":"Include ZRESOURCE_TOP","technicalName":"ZRESOURCE_TOP","group":"PROG"},"edge":{"from":36282,"id":"36282-103916","to":103916,"label":null},"to":{"isCustom":false,"id":103916,"label":"TABL JEST","title":"Individual Object Status","technicalName":"JEST","group":"TABL"}}},{"link":{"from":{"isCustom":true,"id":36282,"label":"INCL ZRESOURCE_TOP","title":"Include ZRESOURCE_TOP","technicalName":"ZRESOURCE_TOP","group":"PROG"},"edge":{"from":36282,"id":"36282-154041","to":154041,"label":null},"to":{"isCustom":false,"id":154041,"label":"TABL TJ02T","title":"System status texts","technicalName":"TJ02T","group":"TABL"}}},{"link":{"from":{"isCustom":true,"id":36282,"label":"INCL ZRESOURCE_TOP","title":"Include ZRESOURCE_TOP","technicalName":"ZRESOURCE_TOP","group":"PROG"},"edge":{"from":36282,"id":"36282-104849","to":104849,"label":null},"to":{"isCustom":false,"id":104849,"label":"TABL KAZY","title":"Interval of Available Capacity","technicalName":"KAZY","group":"TABL"}}},{"link":{"from":{"isCustom":true,"id":36282,"label":"INCL ZRESOURCE_TOP","title":"Include ZRESOURCE_TOP","technicalName":"ZRESOURCE_TOP","group":"PROG"},"edge":{"from":36282,"id":"36282-79263","to":79263,"label":null},"to":{"isCustom":false,"id":79263,"label":"TABL AFVU","title":"DB structure of the user fields of the operation","technicalName":"AFVU","group":"TABL"}}},{"link":{"from":{"isCustom":true,"id":36282,"label":"INCL ZRESOURCE_TOP","title":"Include ZRESOURCE_TOP","technicalName":"ZRESOURCE_TOP","group":"PROG"},"edge":{"from":36282,"id":"36282-86452","to":86452,"label":null},"to":{"isCustom":false,"id":86452,"label":"TABL CRHD","title":"Work Center Header","technicalName":"CRHD","group":"TABL"}}},{"link":{"from":{"isCustom":true,"id":36282,"label":"INCL ZRESOURCE_TOP","title":"Include ZRESOURCE_TOP","technicalName":"ZRESOURCE_TOP","group":"PROG"},"edge":{"from":36282,"id":"36282-80432","to":80432,"label":null},"to":{"isCustom":false,"id":80432,"label":"TABL AUFK","title":"Order master data","technicalName":"AUFK","group":"TABL"}}},{"link":{"from":{"isCustom":true,"id":36282,"label":"INCL ZRESOURCE_TOP","title":"Include ZRESOURCE_TOP","technicalName":"ZRESOURCE_TOP","group":"PROG"},"edge":{"from":36282,"id":"36282-114452","to":114452,"label":null},"to":{"isCustom":false,"id":114452,"label":"TABL PA0002","title":"HR Master Record: Infotype 0002 (Personal Data)","technicalName":"PA0002","group":"TABL"}}},{"link":{"from":{"isCustom":true,"id":36282,"label":"INCL ZRESOURCE_TOP","title":"Include ZRESOURCE_TOP","technicalName":"ZRESOURCE_TOP","group":"PROG"},"edge":{"from":36282,"id":"36282-67174","to":67174,"label":null},"to":{"isCustom":true,"id":67174,"label":"TABL ZENTTYPE","title":"Evaluation interval for zresource table","technicalName":"ZENTTYPE","group":"TABL"}}},{"link":{"from":{"isCustom":true,"id":36282,"label":"INCL ZRESOURCE_TOP","title":"Include ZRESOURCE_TOP","technicalName":"ZRESOURCE_TOP","group":"PROG"},"edge":{"from":36282,"id":"36282-104545","to":104545,"label":null},"to":{"isCustom":false,"id":104545,"label":"TABL JSTO","title":"Status object information","technicalName":"JSTO","group":"TABL"}}},{"link":{"from":{"isCustom":true,"id":36282,"label":"INCL ZRESOURCE_TOP","title":"Include ZRESOURCE_TOP","technicalName":"ZRESOURCE_TOP","group":"PROG"},"edge":{"from":36282,"id":"36282-60732","to":60732,"label":null},"to":{"isCustom":true,"id":60732,"label":"STRU ZPEOPLE","title":"People belogning to a list of work centres","technicalName":"ZPEOPLE","group":"STRU"}}},{"link":{"from":{"isCustom":true,"id":36282,"label":"INCL ZRESOURCE_TOP","title":"Include ZRESOURCE_TOP","technicalName":"ZRESOURCE_TOP","group":"PROG"},"edge":{"from":36282,"id":"36282-356952","to":356952,"label":null},"to":{"isCustom":false,"id":356952,"label":"STRU ISTATUS_RANGE","title":"Range table for status values","technicalName":"ISTATUS_RANGE","group":"STRU"}}},{"link":{"from":{"isCustom":true,"id":36282,"label":"INCL ZRESOURCE_TOP","title":"Include ZRESOURCE_TOP","technicalName":"ZRESOURCE_TOP","group":"PROG"},"edge":{"from":36282,"id":"36282-478775","to":478775,"label":null},"to":{"isCustom":false,"id":478775,"label":"STRU TEXTPOOL","title":"ABAP Text Pool Definition","technicalName":"TEXTPOOL","group":"STRU"}}},{"link":{"from":{"isCustom":true,"id":36282,"label":"INCL ZRESOURCE_TOP","title":"Include ZRESOURCE_TOP","technicalName":"ZRESOURCE_TOP","group":"PROG"},"edge":{"from":36282,"id":"36282-334677","to":334677,"label":null},"to":{"isCustom":false,"id":334677,"label":"STRU HELP_VALUE","title":"Structure or Function Module HELP_VALUE_GET_FOR_TABLE","technicalName":"HELP_VALUE","group":"STRU"}}},{"link":{"from":{"isCustom":true,"id":36282,"label":"INCL ZRESOURCE_TOP","title":"Include ZRESOURCE_TOP","technicalName":"ZRESOURCE_TOP","group":"PROG"},"edge":{"from":36282,"id":"36282-59539","to":59539,"label":null},"to":{"isCustom":true,"id":59539,"label":"STRU ZZOBJ_STAT","title":"Object number and status","technicalName":"ZZOBJ_STAT","group":"STRU"}}},{"link":{"from":{"isCustom":true,"id":36282,"label":"INCL ZRESOURCE_TOP","title":"Include ZRESOURCE_TOP","technicalName":"ZRESOURCE_TOP","group":"PROG"},"edge":{"from":36282,"id":"36282-59676","to":59676,"label":null},"to":{"isCustom":true,"id":59676,"label":"STRU ZWKCENTRES","title":"Work centres structure for Capacity Evaluation","technicalName":"ZWKCENTRES","group":"STRU"}}},{"link":{"from":{"isCustom":true,"id":36282,"label":"INCL ZRESOURCE_TOP","title":"Include ZRESOURCE_TOP","technicalName":"ZRESOURCE_TOP","group":"PROG"},"edge":{"from":36282,"id":"36282-280933","to":280933,"label":null},"to":{"isCustom":false,"id":280933,"label":"STRU DISVARIANT","title":"Layout (External Use)","technicalName":"DISVARIANT","group":"STRU"}}},{"link":{"from":{"isCustom":true,"id":36282,"label":"INCL ZRESOURCE_TOP","title":"Include ZRESOURCE_TOP","technicalName":"ZRESOURCE_TOP","group":"PROG"},"edge":{"from":36282,"id":"36282-1069796","to":1069796,"label":null},"to":{"isCustom":false,"id":1069796,"label":"DTEL RSMPE-FUNC","title":null,"technicalName":"FUNC","group":"DTEL"}}},{"link":{"from":{"isCustom":true,"id":36282,"label":"INCL ZRESOURCE_TOP","title":"Include ZRESOURCE_TOP","technicalName":"ZRESOURCE_TOP","group":"PROG"},"edge":{"from":36282,"id":"36282-1070526","to":1070526,"label":null},"to":{"isCustom":false,"id":1070526,"label":"DTEL TJ30T-TXT04","title":null,"technicalName":"TXT04","group":"DTEL"}}},{"link":{"from":{"isCustom":true,"id":36282,"label":"INCL ZRESOURCE_TOP","title":"Include ZRESOURCE_TOP","technicalName":"ZRESOURCE_TOP","group":"PROG"},"edge":{"from":36282,"id":"36282-1066315","to":1066315,"label":null},"to":{"isCustom":false,"id":1066315,"label":"DTEL AFVV-SSAVD","title":null,"technicalName":"SSAVD","group":"DTEL"}}},{"link":{"from":{"isCustom":true,"id":36282,"label":"INCL ZRESOURCE_TOP","title":"Include ZRESOURCE_TOP","technicalName":"ZRESOURCE_TOP","group":"PROG"},"edge":{"from":36282,"id":"36282-1064727","to":1064727,"label":null},"to":{"isCustom":false,"id":1064727,"label":"DTEL J_TXT04","title":null,"technicalName":"J_TXT04","group":"DTEL"}}},{"link":{"from":{"isCustom":true,"id":36282,"label":"INCL ZRESOURCE_TOP","title":"Include ZRESOURCE_TOP","technicalName":"ZRESOURCE_TOP","group":"PROG"},"edge":{"from":36282,"id":"36282-1066099","to":1066099,"label":null},"to":{"isCustom":false,"id":1066099,"label":"DTEL KAZY-DATUB","title":null,"technicalName":"DATUB","group":"DTEL"}}},{"link":{"from":{"isCustom":true,"id":36282,"label":"INCL ZRESOURCE_TOP","title":"Include ZRESOURCE_TOP","technicalName":"ZRESOURCE_TOP","group":"PROG"},"edge":{"from":36282,"id":"36282-1066159","to":1066159,"label":null},"to":{"isCustom":false,"id":1066159,"label":"DTEL GUI_CODE","title":null,"technicalName":"GUI_CODE","group":"DTEL"}}},{"link":{"from":{"isCustom":true,"id":36282,"label":"INCL ZRESOURCE_TOP","title":"Include ZRESOURCE_TOP","technicalName":"ZRESOURCE_TOP","group":"PROG"},"edge":{"from":36282,"id":"36282-1064832","to":1064832,"label":null},"to":{"isCustom":false,"id":1064832,"label":"DTEL T002-SPRAS","title":null,"technicalName":"SPRAS","group":"DTEL"}}},{"link":{"from":{"isCustom":true,"id":36282,"label":"INCL ZRESOURCE_TOP","title":"Include ZRESOURCE_TOP","technicalName":"ZRESOURCE_TOP","group":"PROG"},"edge":{"from":36282,"id":"36282-1065631","to":1065631,"label":null},"to":{"isCustom":false,"id":1065631,"label":"DTEL SYUCOMM","title":null,"technicalName":"SYUCOMM","group":"DTEL"}}},{"link":{"from":{"isCustom":true,"id":36282,"label":"INCL ZRESOURCE_TOP","title":"Include ZRESOURCE_TOP","technicalName":"ZRESOURCE_TOP","group":"PROG"},"edge":{"from":36282,"id":"36282-1064874","to":1064874,"label":null},"to":{"isCustom":false,"id":1064874,"label":"DTEL DD02L-TABNAME","title":null,"technicalName":"TABNAME","group":"DTEL"}}},{"link":{"from":{"isCustom":true,"id":36282,"label":"INCL ZRESOURCE_TOP","title":"Include ZRESOURCE_TOP","technicalName":"ZRESOURCE_TOP","group":"PROG"},"edge":{"from":36282,"id":"36282-1065302","to":1065302,"label":null},"to":{"isCustom":false,"id":1065302,"label":"DTEL DATS","title":null,"technicalName":"DATS","group":"DTEL"}}},{"link":{"from":{"isCustom":true,"id":36282,"label":"INCL ZRESOURCE_TOP","title":"Include ZRESOURCE_TOP","technicalName":"ZRESOURCE_TOP","group":"PROG"},"edge":{"from":36282,"id":"36282-1064868","to":1064868,"label":null},"to":{"isCustom":false,"id":1064868,"label":"DTEL DFIES-FIELDNAME","title":null,"technicalName":"FIELDNAME","group":"DTEL"}}},{"link":{"from":{"isCustom":true,"id":47546,"label":"PROG ZRESOURCE","title":"Capacity Evaluation Report - By Work Center","technicalName":"ZRESOURCE","group":"PROG"},"edge":{"from":47546,"id":"47546-978361","to":978361,"label":null},"to":{"isCustom":false,"id":978361,"label":"FUNC LSALVU17","title":null,"technicalName":"LSALVU17","group":"PROG"}}},{"link":{"from":{"isCustom":true,"id":47546,"label":"PROG ZRESOURCE","title":"Capacity Evaluation Report - By Work Center","technicalName":"ZRESOURCE","group":"PROG"},"edge":{"from":47546,"id":"47546-978364","to":978364,"label":null},"to":{"isCustom":false,"id":978364,"label":"FUNC LSALVU20","title":null,"technicalName":"LSALVU20","group":"PROG"}}},{"link":{"from":{"isCustom":true,"id":47546,"label":"PROG ZRESOURCE","title":"Capacity Evaluation Report - By Work Center","technicalName":"ZRESOURCE","group":"PROG"},"edge":{"from":47546,"id":"47546-675345","to":675345,"label":null},"to":{"isCustom":false,"id":675345,"label":"FUNC LBDLSU01","title":null,"technicalName":"LBDLSU01","group":"PROG"}}},{"link":{"from":{"isCustom":true,"id":47546,"label":"PROG ZRESOURCE","title":"Capacity Evaluation Report - By Work Center","technicalName":"ZRESOURCE","group":"PROG"},"edge":{"from":47546,"id":"47546-725000","to":725000,"label":null},"to":{"isCustom":false,"id":725000,"label":"FUNC LCR06U11","title":null,"technicalName":"LCR06U11","group":"PROG"}}},{"link":{"from":{"isCustom":true,"id":47546,"label":"PROG ZRESOURCE","title":"Capacity Evaluation Report - By Work Center","technicalName":"ZRESOURCE","group":"PROG"},"edge":{"from":47546,"id":"47546-27915","to":27915,"label":null},"to":{"isCustom":true,"id":27915,"label":"FUNC LZPCCU01","title":"erweiterte Tabellenpflege untere Ebene","technicalName":"LZPCCU01","group":"PROG"}}},{"link":{"from":{"isCustom":true,"id":27915,"label":"FUNC LZPCCU01","title":"erweiterte Tabellenpflege untere Ebene","technicalName":"LZPCCU01","group":"PROG"},"edge":{"from":27915,"id":"27915-114452","to":114452,"label":null},"to":{"isCustom":false,"id":114452,"label":"TABL PA0002","title":"HR Master Record: Infotype 0002 (Personal Data)","technicalName":"PA0002","group":"TABL"}}},{"link":{"from":{"isCustom":true,"id":27915,"label":"FUNC LZPCCU01","title":"erweiterte Tabellenpflege untere Ebene","technicalName":"LZPCCU01","group":"PROG"},"edge":{"from":27915,"id":"27915-99023","to":99023,"label":null},"to":{"isCustom":false,"id":99023,"label":"TABL HRP1001","title":"Infotype 1001 DB Table","technicalName":"HRP1001","group":"TABL"}}},{"link":{"from":{"isCustom":true,"id":47546,"label":"PROG ZRESOURCE","title":"Capacity Evaluation Report - By Work Center","technicalName":"ZRESOURCE","group":"PROG"},"edge":{"from":47546,"id":"47546-899056","to":899056,"label":null},"to":{"isCustom":false,"id":899056,"label":"FUNC LMLSHU29","title":null,"technicalName":"LMLSHU29","group":"PROG"}}},{"link":{"from":{"isCustom":true,"id":47546,"label":"PROG ZRESOURCE","title":"Capacity Evaluation Report - By Work Center","technicalName":"ZRESOURCE","group":"PROG"},"edge":{"from":47546,"id":"47546-29814","to":29814,"label":null},"to":{"isCustom":true,"id":29814,"label":"FUNC LZVPSU01","title":"Calculate work days","technicalName":"LZVPSU01","group":"PROG"}}},{"link":{"from":{"isCustom":true,"id":29814,"label":"FUNC LZVPSU01","title":"Calculate work days","technicalName":"LZVPSU01","group":"PROG"},"edge":{"from":29814,"id":"29814-456594","to":456594,"label":null},"to":{"isCustom":false,"id":456594,"label":"STRU SCAL","title":"Structure for factory calendar function modules","technicalName":"SCAL","group":"STRU"}}},{"link":{"from":{"isCustom":true,"id":29814,"label":"FUNC LZVPSU01","title":"Calculate work days","technicalName":"LZVPSU01","group":"PROG"},"edge":{"from":29814,"id":"29814-980185","to":980185,"label":null},"to":{"isCustom":false,"id":980185,"label":"FUNC LSCALU01","title":null,"technicalName":"LSCALU01","group":"PROG"}}},{"link":{"from":{"isCustom":true,"id":29814,"label":"FUNC LZVPSU01","title":"Calculate work days","technicalName":"LZVPSU01","group":"PROG"},"edge":{"from":29814,"id":"29814-980190","to":980190,"label":null},"to":{"isCustom":false,"id":980190,"label":"FUNC LSCALU06","title":null,"technicalName":"LSCALU06","group":"PROG"}}},{"link":{"from":{"isCustom":true,"id":29814,"label":"FUNC LZVPSU01","title":"Calculate work days","technicalName":"LZVPSU01","group":"PROG"},"edge":{"from":29814,"id":"29814-1064786","to":1064786,"label":null},"to":{"isCustom":false,"id":1064786,"label":"DTEL SY-DATUM","title":null,"technicalName":"DATUM","group":"DTEL"}}},{"link":{"from":{"isCustom":true,"id":47546,"label":"PROG ZRESOURCE","title":"Capacity Evaluation Report - By Work Center","technicalName":"ZRESOURCE","group":"PROG"},"edge":{"from":47546,"id":"47546-839989","to":839989,"label":null},"to":{"isCustom":false,"id":839989,"label":"FUNC LIBXXU05","title":null,"technicalName":"LIBXXU05","group":"PROG"}}},{"link":{"from":{"isCustom":true,"id":47546,"label":"PROG ZRESOURCE","title":"Capacity Evaluation Report - By Work Center","technicalName":"ZRESOURCE","group":"PROG"},"edge":{"from":47546,"id":"47546-1075463","to":1075463,"label":null},"to":{"isCustom":false,"id":1075463,"label":"FUNC ##/MRSS/SGE_RESOURCE_TO_EMPLOYEE","title":null,"technicalName":"##/MRSS/SGE_RESOURCE_TO_EMPLOYEE","group":"PROG"}}},{"link":{"from":{"isCustom":true,"id":47546,"label":"PROG ZRESOURCE","title":"Capacity Evaluation Report - By Work Center","technicalName":"ZRESOURCE","group":"PROG"},"edge":{"from":47546,"id":"47546-694704","to":694704,"label":null},"to":{"isCustom":false,"id":694704,"label":"FUNC LCAPPU03","title":null,"technicalName":"LCAPPU03","group":"PROG"}}},{"link":{"from":{"isCustom":true,"id":47546,"label":"PROG ZRESOURCE","title":"Capacity Evaluation Report - By Work Center","technicalName":"ZRESOURCE","group":"PROG"},"edge":{"from":47546,"id":"47546-835147","to":835147,"label":null},"to":{"isCustom":false,"id":835147,"label":"FUNC LHRTRV_STATU04","title":null,"technicalName":"LHRTRV_STATU04","group":"PROG"}}},{"link":{"from":{"isCustom":true,"id":47546,"label":"PROG ZRESOURCE","title":"Capacity Evaluation Report - By Work Center","technicalName":"ZRESOURCE","group":"PROG"},"edge":{"from":47546,"id":"47546-997198","to":997198,"label":null},"to":{"isCustom":false,"id":997198,"label":"FUNC LSLVC_FULLSCREENU01","title":null,"technicalName":"LSLVC_FULLSCREENU01","group":"PROG"}}},{"link":{"from":{"isCustom":true,"id":47546,"label":"PROG ZRESOURCE","title":"Capacity Evaluation Report - By Work Center","technicalName":"ZRESOURCE","group":"PROG"},"edge":{"from":47546,"id":"47546-978347","to":978347,"label":null},"to":{"isCustom":false,"id":978347,"label":"FUNC LSALVU03","title":null,"technicalName":"LSALVU03","group":"PROG"}}},{"link":{"from":{"isCustom":true,"id":47546,"label":"PROG ZRESOURCE","title":"Capacity Evaluation Report - By Work Center","technicalName":"ZRESOURCE","group":"PROG"},"edge":{"from":47546,"id":"47546-679845","to":679845,"label":null},"to":{"isCustom":false,"id":679845,"label":"FUNC LBSVAU12","title":null,"technicalName":"LBSVAU12","group":"PROG"}}},{"link":{"from":{"isCustom":true,"id":47546,"label":"PROG ZRESOURCE","title":"Capacity Evaluation Report - By Work Center","technicalName":"ZRESOURCE","group":"PROG"},"edge":{"from":47546,"id":"47546-801928","to":801928,"label":null},"to":{"isCustom":false,"id":801928,"label":"FUNC LFVOZU04","title":null,"technicalName":"LFVOZU04","group":"PROG"}}},{"link":{"from":{"isCustom":true,"id":47546,"label":"PROG ZRESOURCE","title":"Capacity Evaluation Report - By Work Center","technicalName":"ZRESOURCE","group":"PROG"},"edge":{"from":47546,"id":"47546-978346","to":978346,"label":null},"to":{"isCustom":false,"id":978346,"label":"FUNC LSALVU02","title":null,"technicalName":"LSALVU02","group":"PROG"}}},{"link":{"from":{"isCustom":true,"id":47546,"label":"PROG ZRESOURCE","title":"Capacity Evaluation Report - By Work Center","technicalName":"ZRESOURCE","group":"PROG"},"edge":{"from":47546,"id":"47546-978349","to":978349,"label":null},"to":{"isCustom":false,"id":978349,"label":"FUNC LSALVU05","title":null,"technicalName":"LSALVU05","group":"PROG"}}},{"link":{"from":{"isCustom":true,"id":47546,"label":"PROG ZRESOURCE","title":"Capacity Evaluation Report - By Work Center","technicalName":"ZRESOURCE","group":"PROG"},"edge":{"from":47546,"id":"47546-992787","to":992787,"label":null},"to":{"isCustom":false,"id":992787,"label":"FUNC LSHL3U02","title":null,"technicalName":"LSHL3U02","group":"PROG"}}},{"link":{"from":{"isCustom":true,"id":47546,"label":"PROG ZRESOURCE","title":"Capacity Evaluation Report - By Work Center","technicalName":"ZRESOURCE","group":"PROG"},"edge":{"from":47546,"id":"47546-1065016","to":1065016,"label":null},"to":{"isCustom":false,"id":1065016,"label":"DTEL J_TXT30","title":null,"technicalName":"J_TXT30","group":"DTEL"}}},{"link":{"from":{"isCustom":true,"id":47546,"label":"PROG ZRESOURCE","title":"Capacity Evaluation Report - By Work Center","technicalName":"ZRESOURCE","group":"PROG"},"edge":{"from":47546,"id":"47546-51056","to":51056,"label":null},"to":{"isCustom":true,"id":51056,"label":"DTEL ZENT","title":"entry type field","technicalName":"ZENT","group":"DTEL"}}},{"link":{"from":{"isCustom":true,"id":47546,"label":"PROG ZRESOURCE","title":"Capacity Evaluation Report - By Work Center","technicalName":"ZRESOURCE","group":"PROG"},"edge":{"from":47546,"id":"47546-1065228","to":1065228,"label":null},"to":{"isCustom":false,"id":1065228,"label":"DTEL SCAL-FACIDATE","title":null,"technicalName":"FACIDATE","group":"DTEL"}}},{"link":{"from":{"isCustom":true,"id":47546,"label":"PROG ZRESOURCE","title":"Capacity Evaluation Report - By Work Center","technicalName":"ZRESOURCE","group":"PROG"},"edge":{"from":47546,"id":"47546-1066099","to":1066099,"label":null},"to":{"isCustom":false,"id":1066099,"label":"DTEL KAZY-DATUB","title":null,"technicalName":"DATUB","group":"DTEL"}}},{"link":{"from":{"isCustom":true,"id":47546,"label":"PROG ZRESOURCE","title":"Capacity Evaluation Report - By Work Center","technicalName":"ZRESOURCE","group":"PROG"},"edge":{"from":47546,"id":"47546-1069402","to":1069402,"label":null},"to":{"isCustom":false,"id":1069402,"label":"DTEL MENGEV","title":null,"technicalName":"MENGEV","group":"DTEL"}}},{"link":{"from":{"isCustom":true,"id":47546,"label":"PROG ZRESOURCE","title":"Capacity Evaluation Report - By Work Center","technicalName":"ZRESOURCE","group":"PROG"},"edge":{"from":47546,"id":"47546-1064920","to":1064920,"label":null},"to":{"isCustom":false,"id":1064920,"label":"DTEL TKA01-KOKRS","title":null,"technicalName":"KOKRS","group":"DTEL"}}},{"link":{"from":{"isCustom":true,"id":47546,"label":"PROG ZRESOURCE","title":"Capacity Evaluation Report - By Work Center","technicalName":"ZRESOURCE","group":"PROG"},"edge":{"from":47546,"id":"47546-1065100","to":1065100,"label":null},"to":{"isCustom":false,"id":1065100,"label":"DTEL PERSNO","title":null,"technicalName":"PERSNO","group":"DTEL"}}},{"link":{"from":{"isCustom":true,"id":47546,"label":"PROG ZRESOURCE","title":"Capacity Evaluation Report - By Work Center","technicalName":"ZRESOURCE","group":"PROG"},"edge":{"from":47546,"id":"47546-1064966","to":1064966,"label":null},"to":{"isCustom":false,"id":1064966,"label":"DTEL T000-LOGSYS","title":null,"technicalName":"LOGSYS","group":"DTEL"}}},{"link":{"from":{"isCustom":true,"id":47546,"label":"PROG ZRESOURCE","title":"Capacity Evaluation Report - By Work Center","technicalName":"ZRESOURCE","group":"PROG"},"edge":{"from":47546,"id":"47546-1064905","to":1064905,"label":null},"to":{"isCustom":false,"id":1064905,"label":"DTEL DF14L-PS_POSID","title":null,"technicalName":"PS_POSID","group":"DTEL"}}},{"link":{"from":{"isCustom":true,"id":47546,"label":"PROG ZRESOURCE","title":"Capacity Evaluation Report - By Work Center","technicalName":"ZRESOURCE","group":"PROG"},"edge":{"from":47546,"id":"47546-1066365","to":1066365,"label":null},"to":{"isCustom":false,"id":1066365,"label":"DTEL PRIOTEXT","title":null,"technicalName":"PRIOTEXT","group":"DTEL"}}},{"link":{"from":{"isCustom":true,"id":47546,"label":"PROG ZRESOURCE","title":"Capacity Evaluation Report - By Work Center","technicalName":"ZRESOURCE","group":"PROG"},"edge":{"from":47546,"id":"47546-1064725","to":1064725,"label":null},"to":{"isCustom":false,"id":1064725,"label":"DTEL J_OBJNR","title":null,"technicalName":"J_OBJNR","group":"DTEL"}}},{"link":{"from":{"isCustom":true,"id":47546,"label":"PROG ZRESOURCE","title":"Capacity Evaluation Report - By Work Center","technicalName":"ZRESOURCE","group":"PROG"},"edge":{"from":47546,"id":"47546-1065648","to":1065648,"label":null},"to":{"isCustom":false,"id":1065648,"label":"DTEL J_STEXT","title":null,"technicalName":"J_STEXT","group":"DTEL"}}},{"link":{"from":{"isCustom":true,"id":47546,"label":"PROG ZRESOURCE","title":"Capacity Evaluation Report - By Work Center","technicalName":"ZRESOURCE","group":"PROG"},"edge":{"from":47546,"id":"47546-1064727","to":1064727,"label":null},"to":{"isCustom":false,"id":1064727,"label":"DTEL J_TXT04","title":null,"technicalName":"J_TXT04","group":"DTEL"}}},{"link":{"from":{"isCustom":true,"id":47546,"label":"PROG ZRESOURCE","title":"Capacity Evaluation Report - By Work Center","technicalName":"ZRESOURCE","group":"PROG"},"edge":{"from":47546,"id":"47546-1064792","to":1064792,"label":null},"to":{"isCustom":false,"id":1064792,"label":"DTEL J_STSMA","title":null,"technicalName":"J_STSMA","group":"DTEL"}}},{"link":{"from":{"isCustom":true,"id":47546,"label":"PROG ZRESOURCE","title":"Capacity Evaluation Report - By Work Center","technicalName":"ZRESOURCE","group":"PROG"},"edge":{"from":47546,"id":"47546-1064790","to":1064790,"label":null},"to":{"isCustom":false,"id":1064790,"label":"DTEL J_ESTAT","title":null,"technicalName":"J_ESTAT","group":"DTEL"}}},{"link":{"from":{"isCustom":true,"id":47546,"label":"PROG ZRESOURCE","title":"Capacity Evaluation Report - By Work Center","technicalName":"ZRESOURCE","group":"PROG"},"edge":{"from":47546,"id":"47546-1064844","to":1064844,"label":null},"to":{"isCustom":false,"id":1064844,"label":"DTEL CHAR4","title":null,"technicalName":"CHAR4","group":"DTEL"}}},{"link":{"from":{"isCustom":true,"id":47546,"label":"PROG ZRESOURCE","title":"Capacity Evaluation Report - By Work Center","technicalName":"ZRESOURCE","group":"PROG"},"edge":{"from":47546,"id":"47546-1066342","to":1066342,"label":null},"to":{"isCustom":false,"id":1066342,"label":"DTEL SMLS_KTEXT","title":null,"technicalName":"SMLS_KTEXT","group":"DTEL"}}},{"link":{"from":{"isCustom":true,"id":47546,"label":"PROG ZRESOURCE","title":"Capacity Evaluation Report - By Work Center","technicalName":"ZRESOURCE","group":"PROG"},"edge":{"from":47546,"id":"47546-1069886","to":1069886,"label":null},"to":{"isCustom":false,"id":1069886,"label":"DTEL SYSUUID_C","title":null,"technicalName":"SYSUUID_C","group":"DTEL"}}},{"link":{"from":{"isCustom":true,"id":47546,"label":"PROG ZRESOURCE","title":"Capacity Evaluation Report - By Work Center","technicalName":"ZRESOURCE","group":"PROG"},"edge":{"from":47546,"id":"47546-1064927","to":1064927,"label":null},"to":{"isCustom":false,"id":1064927,"label":"DTEL J_STATUS","title":null,"technicalName":"J_STATUS","group":"DTEL"}}},{"link":{"from":{"isCustom":true,"id":47546,"label":"PROG ZRESOURCE","title":"Capacity Evaluation Report - By Work Center","technicalName":"ZRESOURCE","group":"PROG"},"edge":{"from":47546,"id":"47546-1065412","to":1065412,"label":null},"to":{"isCustom":false,"id":1065412,"label":"DTEL SY-LANGU","title":null,"technicalName":"LANGU","group":"DTEL"}}},{"link":{"from":{"isCustom":true,"id":47546,"label":"PROG ZRESOURCE","title":"Capacity Evaluation Report - By Work Center","technicalName":"ZRESOURCE","group":"PROG"},"edge":{"from":47546,"id":"47546-1065804","to":1065804,"label":null},"to":{"isCustom":false,"id":1065804,"label":"DTEL SLIS_VARI","title":null,"technicalName":"SLIS_VARI","group":"DTEL"}}},{"link":{"from":{"isCustom":true,"id":47546,"label":"PROG ZRESOURCE","title":"Capacity Evaluation Report - By Work Center","technicalName":"ZRESOURCE","group":"PROG"},"edge":{"from":47546,"id":"47546-1064724","to":1064724,"label":null},"to":{"isCustom":false,"id":1064724,"label":"DTEL J_ISTAT","title":null,"technicalName":"J_ISTAT","group":"DTEL"}}},{"link":{"from":{"isCustom":true,"id":47546,"label":"PROG ZRESOURCE","title":"Capacity Evaluation Report - By Work Center","technicalName":"ZRESOURCE","group":"PROG"},"edge":{"from":47546,"id":"47546-1069401","to":1069401,"label":null},"to":{"isCustom":false,"id":1069401,"label":"DTEL CR_HNAME","title":null,"technicalName":"CR_HNAME","group":"DTEL"}}},{"link":{"from":{"isCustom":true,"id":47546,"label":"PROG ZRESOURCE","title":"Capacity Evaluation Report - By Work Center","technicalName":"ZRESOURCE","group":"PROG"},"edge":{"from":47546,"id":"47546-1066364","to":1066364,"label":null},"to":{"isCustom":false,"id":1066364,"label":"DTEL NW_PRIO","title":null,"technicalName":"NW_PRIO","group":"DTEL"}}},{"link":{"from":{"isCustom":true,"id":47546,"label":"PROG ZRESOURCE","title":"Capacity Evaluation Report - By Work Center","technicalName":"ZRESOURCE","group":"PROG"},"edge":{"from":47546,"id":"47546-1074478","to":1074478,"label":null},"to":{"isCustom":false,"id":1074478,"label":"DTEL ZENTTYPE-ENT_TYPE","title":null,"technicalName":"ENT_TYPE","group":"DTEL"}}},{"link":{"from":{"isCustom":true,"id":47546,"label":"PROG ZRESOURCE","title":"Capacity Evaluation Report - By Work Center","technicalName":"ZRESOURCE","group":"PROG"},"edge":{"from":47546,"id":"47546-1070636","to":1070636,"label":null},"to":{"isCustom":false,"id":1070636,"label":"DTEL JEST-STAT","title":null,"technicalName":"STAT","group":"DTEL"}}},{"link":{"from":{"isCustom":true,"id":47546,"label":"PROG ZRESOURCE","title":"Capacity Evaluation Report - By Work Center","technicalName":"ZRESOURCE","group":"PROG"},"edge":{"from":47546,"id":"47546-1072551","to":1072551,"label":null},"to":{"isCustom":false,"id":1072551,"label":"DTEL SY-TIMLO","title":null,"technicalName":"TIMLO","group":"DTEL"}}},{"link":{"from":{"isCustom":true,"id":47546,"label":"PROG ZRESOURCE","title":"Capacity Evaluation Report - By Work Center","technicalName":"ZRESOURCE","group":"PROG"},"edge":{"from":47546,"id":"47546-1070618","to":1070618,"label":null},"to":{"isCustom":false,"id":1070618,"label":"DTEL RKD_S_SEIG-LOW","title":null,"technicalName":"LOW","group":"DTEL"}}},{"link":{"from":{"isCustom":true,"id":47546,"label":"PROG ZRESOURCE","title":"Capacity Evaluation Report - By Work Center","technicalName":"ZRESOURCE","group":"PROG"},"edge":{"from":47546,"id":"47546-1072269","to":1072269,"label":null},"to":{"isCustom":false,"id":1072269,"label":"DTEL BAPI0004_2-CO_AREA","title":null,"technicalName":"CO_AREA","group":"DTEL"}}},{"link":{"from":{"isCustom":true,"id":47546,"label":"PROG ZRESOURCE","title":"Capacity Evaluation Report - By Work Center","technicalName":"ZRESOURCE","group":"PROG"},"edge":{"from":47546,"id":"47546-1070666","to":1070666,"label":null},"to":{"isCustom":false,"id":1070666,"label":"DTEL TJ30T-TXT30","title":null,"technicalName":"TXT30","group":"DTEL"}}},{"link":{"from":{"isCustom":true,"id":47546,"label":"PROG ZRESOURCE","title":"Capacity Evaluation Report - By Work Center","technicalName":"ZRESOURCE","group":"PROG"},"edge":{"from":47546,"id":"47546-1067749","to":1067749,"label":null},"to":{"isCustom":false,"id":1067749,"label":"DTEL PRPS-POSID","title":null,"technicalName":"POSID","group":"DTEL"}}},{"link":{"from":{"isCustom":true,"id":47546,"label":"PROG ZRESOURCE","title":"Capacity Evaluation Report - By Work Center","technicalName":"ZRESOURCE","group":"PROG"},"edge":{"from":47546,"id":"47546-1071416","to":1071416,"label":null},"to":{"isCustom":false,"id":1071416,"label":"DTEL TJ30T-STSMA","title":null,"technicalName":"STSMA","group":"DTEL"}}},{"link":{"from":{"isCustom":true,"id":47546,"label":"PROG ZRESOURCE","title":"Capacity Evaluation Report - By Work Center","technicalName":"ZRESOURCE","group":"PROG"},"edge":{"from":47546,"id":"47546-1068377","to":1068377,"label":null},"to":{"isCustom":false,"id":1068377,"label":"DTEL DISVARIANT-VARIANT","title":null,"technicalName":"VARIANT","group":"DTEL"}}},{"link":{"from":{"isCustom":true,"id":47546,"label":"PROG ZRESOURCE","title":"Capacity Evaluation Report - By Work Center","technicalName":"ZRESOURCE","group":"PROG"},"edge":{"from":47546,"id":"47546-1070303","to":1070303,"label":null},"to":{"isCustom":false,"id":1070303,"label":"DTEL FELD-NAME","title":null,"technicalName":"NAME","group":"DTEL"}}},{"link":{"from":{"isCustom":true,"id":47546,"label":"PROG ZRESOURCE","title":"Capacity Evaluation Report - By Work Center","technicalName":"ZRESOURCE","group":"PROG"},"edge":{"from":47546,"id":"47546-1070968","to":1070968,"label":null},"to":{"isCustom":false,"id":1070968,"label":"DTEL ZPV_ALV_STRUCT-ESTAT","title":null,"technicalName":"ESTAT","group":"DTEL"}}},{"link":{"from":{"isCustom":true,"id":47546,"label":"PROG ZRESOURCE","title":"Capacity Evaluation Report - By Work Center","technicalName":"ZRESOURCE","group":"PROG"},"edge":{"from":47546,"id":"47546-1070525","to":1070525,"label":null},"to":{"isCustom":false,"id":1070525,"label":"DTEL TJ07-ISTAT","title":null,"technicalName":"ISTAT","group":"DTEL"}}},{"link":{"from":{"isCustom":true,"id":47546,"label":"PROG ZRESOURCE","title":"Capacity Evaluation Report - By Work Center","technicalName":"ZRESOURCE","group":"PROG"},"edge":{"from":47546,"id":"47546-1070630","to":1070630,"label":null},"to":{"isCustom":false,"id":1070630,"label":"DTEL MSEG-MENGE","title":null,"technicalName":"MENGE","group":"DTEL"}}},{"link":{"from":{"isCustom":true,"id":47546,"label":"PROG ZRESOURCE","title":"Capacity Evaluation Report - By Work Center","technicalName":"ZRESOURCE","group":"PROG"},"edge":{"from":47546,"id":"47546-1067409","to":1067409,"label":null},"to":{"isCustom":false,"id":1067409,"label":"DTEL COST-OBJNR","title":null,"technicalName":"OBJNR","group":"DTEL"}}},{"link":{"from":{"isCustom":true,"id":47546,"label":"PROG ZRESOURCE","title":"Capacity Evaluation Report - By Work Center","technicalName":"ZRESOURCE","group":"PROG"},"edge":{"from":47546,"id":"47546-1071479","to":1071479,"label":null},"to":{"isCustom":false,"id":1071479,"label":"DTEL TCN7T-NPRIO","title":null,"technicalName":"NPRIO","group":"DTEL"}}},{"link":{"from":{"isCustom":true,"id":47546,"label":"PROG ZRESOURCE","title":"Capacity Evaluation Report - By Work Center","technicalName":"ZRESOURCE","group":"PROG"},"edge":{"from":47546,"id":"47546-1070526","to":1070526,"label":null},"to":{"isCustom":false,"id":1070526,"label":"DTEL TJ30T-TXT04","title":null,"technicalName":"TXT04","group":"DTEL"}}},{"link":{"from":{"isCustom":true,"id":47546,"label":"PROG ZRESOURCE","title":"Capacity Evaluation Report - By Work Center","technicalName":"ZRESOURCE","group":"PROG"},"edge":{"from":47546,"id":"47546-1071418","to":1071418,"label":null},"to":{"isCustom":false,"id":1071418,"label":"DTEL SY-LINSZ","title":null,"technicalName":"LINSZ","group":"DTEL"}}},{"link":{"from":{"isCustom":true,"id":47546,"label":"PROG ZRESOURCE","title":"Capacity Evaluation Report - By Work Center","technicalName":"ZRESOURCE","group":"PROG"},"edge":{"from":47546,"id":"47546-1069895","to":1069895,"label":null},"to":{"isCustom":false,"id":1069895,"label":"DTEL BSVX-STTXT","title":null,"technicalName":"STTXT","group":"DTEL"}}},{"link":{"from":{"isCustom":true,"id":47546,"label":"PROG ZRESOURCE","title":"Capacity Evaluation Report - By Work Center","technicalName":"ZRESOURCE","group":"PROG"},"edge":{"from":47546,"id":"47546-1071082","to":1071082,"label":null},"to":{"isCustom":false,"id":1071082,"label":"DTEL SY-DATLO","title":null,"technicalName":"DATLO","group":"DTEL"}}},{"link":{"from":{"isCustom":true,"id":47546,"label":"PROG ZRESOURCE","title":"Capacity Evaluation Report - By Work Center","technicalName":"ZRESOURCE","group":"PROG"},"edge":{"from":47546,"id":"47546-56598","to":56598,"label":null},"to":{"isCustom":true,"id":56598,"label":"DTEL AUFK-ZZTRIGGER","title":"CI_AUFK structure Trigger field","technicalName":"ZZTRIGGER","group":"DTEL"}}},{"link":{"from":{"isCustom":true,"id":47546,"label":"PROG ZRESOURCE","title":"Capacity Evaluation Report - By Work Center","technicalName":"ZRESOURCE","group":"PROG"},"edge":{"from":47546,"id":"47546-1066437","to":1066437,"label":null},"to":{"isCustom":false,"id":1066437,"label":"DTEL MLTX-KTEXT","title":null,"technicalName":"KTEXT","group":"DTEL"}}},{"link":{"from":{"isCustom":true,"id":47546,"label":"PROG ZRESOURCE","title":"Capacity Evaluation Report - By Work Center","technicalName":"ZRESOURCE","group":"PROG"},"edge":{"from":47546,"id":"47546-1070665","to":1070665,"label":null},"to":{"isCustom":false,"id":1070665,"label":"DTEL SY-UCOMM","title":null,"technicalName":"UCOMM","group":"DTEL"}}},{"link":{"from":{"isCustom":true,"id":47546,"label":"PROG ZRESOURCE","title":"Capacity Evaluation Report - By Work Center","technicalName":"ZRESOURCE","group":"PROG"},"edge":{"from":47546,"id":"47546-27938","to":27938,"label":null},"to":{"isCustom":true,"id":27938,"label":"FUNC LZPES3U04","title":"GG-Mat: Vortag zu einem Datum bestimmen","technicalName":"LZPES3U04","group":"PROG"}}},{"link":{"from":{"isCustom":true,"id":27938,"label":"FUNC LZPES3U04","title":"GG-Mat: Vortag zu einem Datum bestimmen","technicalName":"LZPES3U04","group":"PROG"},"edge":{"from":27938,"id":"27938-1064786","to":1064786,"label":null},"to":{"isCustom":false,"id":1064786,"label":"DTEL SY-DATUM","title":null,"technicalName":"DATUM","group":"DTEL"}}},{"link":{"from":{"isCustom":true,"id":47546,"label":"PROG ZRESOURCE","title":"Capacity Evaluation Report - By Work Center","technicalName":"ZRESOURCE","group":"PROG"},"edge":{"from":47546,"id":"47546-978363","to":978363,"label":null},"to":{"isCustom":false,"id":978363,"label":"FUNC LSALVU19","title":null,"technicalName":"LSALVU19","group":"PROG"}}},{"link":{"from":{"isCustom":true,"id":70129,"label":"TRAN ZRESOURCE","title":"Capacity Evaluation Report","technicalName":"ZRESOURCE","group":"TRAN"},"edge":{"from":70129,"id":"70129-47546","to":47546,"label":null},"to":{"isCustom":true,"id":47546,"label":"PROG ZRESOURCE","title":"Capacity Evaluation Report - By Work Center","technicalName":"ZRESOURCE","group":"PROG"}}}]